LICENSE
README.md
setup.cfg
setup.py
d1ct/__init__.py
d1ct.egg-info/PKG-INFO
d1ct.egg-info/SOURCES.txt
d1ct.egg-info/dependency_links.txt
d1ct.egg-info/top_level.txt