Metadata-Version: 2.1
Name: d1ct
Version: 1.0.5
Summary: dict implementation supporting attribute access, recursion, json, hashable, subclass, metaclass
Home-page: https://www.github.com/ultrafunkamsterdam/d1ct
Author: UltrafunkAmsterdam
Author-email: info@ultrafunk.nl
License: GPL
License-File: LICENSE
